Param_Hello.py
Param_Hello-0.0.2.dist-info/LICENSE
Param_Hello-0.0.2.dist-info/METADATA
Param_Hello-0.0.2.dist-info/WHEEL
Param_Hello-0.0.2.dist-info/top_level.txt
Param_Hello-0.0.2.dist-info/RECORD
