Metadata-Version: 2.1
Name: Param-Hello
Version: 0.0.2
Summary: Say Hello!
Home-page: https://github.com/Param542
Author: Param
Author-email: parme542@gmail.com
License: UNKNOWN
Platform: UNKNOWN
Classifier: Programming Language :: Python :: 3
Classifier: Programming Language :: Python :: 3.6
Classifier: Programming Language :: Python :: 3.7
Classifier: License :: OSI Approved :: MIT License
Classifier: Operating System :: OS Independent
